socketio-stubs/__init__.pyi
socketio-stubs/_types.pyi
socketio-stubs/admin.pyi
socketio-stubs/asgi.pyi
socketio-stubs/async_admin.pyi
socketio-stubs/async_aiopika_manager.pyi
socketio-stubs/async_client.pyi
socketio-stubs/async_manager.pyi
socketio-stubs/async_namespace.pyi
socketio-stubs/async_pubsub_manager.pyi
socketio-stubs/async_redis_manager.pyi
socketio-stubs/async_server.pyi
socketio-stubs/async_simple_client.pyi
socketio-stubs/base_client.pyi
socketio-stubs/base_manager.pyi
socketio-stubs/base_namespace.pyi
socketio-stubs/base_server.pyi
socketio-stubs/client.pyi
socketio-stubs/exceptions.pyi
socketio-stubs/kafka_manager.pyi
socketio-stubs/kombu_manager.pyi
socketio-stubs/manager.pyi
socketio-stubs/middleware.pyi
socketio-stubs/msgpack_packet.pyi
socketio-stubs/namespace.pyi
socketio-stubs/packet.pyi
socketio-stubs/pubsub_manager.pyi
socketio-stubs/py.typed
socketio-stubs/redis_manager.pyi
socketio-stubs/server.pyi
socketio-stubs/simple_client.pyi
socketio-stubs/tornado.pyi
socketio-stubs/zmq_manager.pyi
python_socketio_stubs-5.16.0.0.20260117.dist-info/METADATA
python_socketio_stubs-5.16.0.0.20260117.dist-info/WHEEL
python_socketio_stubs-5.16.0.0.20260117.dist-info/licenses/LICENSE
python_socketio_stubs-5.16.0.0.20260117.dist-info/RECORD
