Metadata-Version: 2.4
Name: python-socketio-stubs
Version: 5.16.0.0.20260117
Summary: python-socketio stubs
Project-URL: Repository, https://github.com/phi-friday/python-socketio-stubs
Author-email: phi <phi.friday@gmail.com>
License-Expression: MIT
License-File: LICENSE
Classifier: Development Status :: 4 - Beta
Classifier: Programming Language :: Python :: 3
Classifier: Programming Language :: Python :: 3.11
Classifier: Programming Language :: Python :: 3.12
Classifier: Programming Language :: Python :: 3.13
Classifier: Programming Language :: Python :: 3.14
Classifier: Programming Language :: Python :: Implementation :: CPython
Classifier: Typing :: Stubs Only
Requires-Python: >=3.11
Requires-Dist: typing-extensions>=4.4.0
Provides-Extra: mypy
Requires-Dist: mypy>=1.19.1; extra == 'mypy'
Provides-Extra: mypy-strict
Requires-Dist: mypy==1.19.1; extra == 'mypy-strict'
Requires-Dist: mypy>=1.19.1; extra == 'mypy-strict'
